fastapi_dapr_helper/__init__.py
fastapi_dapr_helper/pubsub.py
fastapi_dapr_helper-0.1.1.dist-info/LICENSE.md
fastapi_dapr_helper-0.1.1.dist-info/WHEEL
fastapi_dapr_helper-0.1.1.dist-info/METADATA
fastapi_dapr_helper-0.1.1.dist-info/RECORD
