Metadata-Version: 2.1
Name: fastapi-dapr-helper
Version: 0.1.1
Summary: 
Author: Clayton Black
Author-email: CBlack@fanatics.com
Requires-Python: >=3.8.1,<4.0.0
Classifier: Programming Language :: Python :: 3
Classifier: Programming Language :: Python :: 3.9
Classifier: Programming Language :: Python :: 3.10
Requires-Dist: fastapi (>=0.95.2,<0.96.0)
